packageManifest/VERSION
packageManifest/__init__.py
packageManifest/manifest.py
packageManifest/globalName/__init__.py
packageManifest/globalName/exclude.py
packageManifest/globalName/include.py
packageManifest/globalName/tests/__init__.py
packageManifest/globalName/tests/testApplyGlobalExclusions.py
packageManifest/globalName/tests/testApplyGlobalInclusions.py
packageManifest/globalName/tests/testGlobalExclude.py
packageManifest/globalName/tests/testGlobalInclude.py
packageManifest/globalName/tests/testGlobalNameYamlExclude.py
packageManifest/globalName/tests/testGlobalNameYamlInclude.py
packageManifest/localName/__init__.py
packageManifest/localName/exclude.py
packageManifest/localName/include.py
packageManifest/localName/tests/__init__.py
packageManifest/localName/tests/testApplyLocalExclusions.py
packageManifest/localName/tests/testApplyLocalInclusions.py
packageManifest/localName/tests/testLocalNameExclude.py
packageManifest/localName/tests/testLocalNameInclude.py
packageManifest/localName/tests/testLocalNameYamlExclude.py
packageManifest/localName/tests/testLocalNameYamlInclude.py
packageManifest/path/__init__.py
packageManifest/path/path.py
packageManifest/path/set.py
packageManifest/path/tests/__init__.py
packageManifest/path/tests/testFilterNotInDirectory.py
packageManifest/path/tests/testMakeRelativePaths.py
packageManifest/path/tests/testPathSet.py
packageManifest/path/tests/testPrependDirectory.py
packageManifest/recursive/__init__.py
packageManifest/recursive/exclude.py
packageManifest/recursive/include.py
packageManifest/recursive/tests/__init__.py
packageManifest/recursive/tests/testApplyRecursiveExclusions.py
packageManifest/recursive/tests/testApplyRecursiveInclusions.py
packageManifest/recursive/tests/testRecursiveExclude.py
packageManifest/recursive/tests/testRecursiveInclude.py
packageManifest/recursive/tests/testRecursiveYamlExclude.py
packageManifest/recursive/tests/testRecursiveYamlInclude.py
packageManifest/tests/__init__.py
packageManifest-1.0.0.dist-info/LICENSE
packageManifest-1.0.0.dist-info/WHEEL
packageManifest-1.0.0.dist-info/METADATA
packageManifest-1.0.0.dist-info/RECORD
