Metadata-Version: 1.2
Name: packageManifest
Version: 1.0.0
Summary: A YAML based file package-manifest framework for defining packages.
Home-page: https://gitlab.com/blueskyjunkie/package-manifest
License: UNKNOWN
Keywords: manifest package distribution file
Author: Russell Smiley
Author-email: im.russell.smiley@gmail.com
Requires-Python: >=3
Classifier: License :: OSI Approved :: GNU General Public License v3 or later (GPLv3+)
Requires-Dist: pyyaml
